hackpi/Auth.py
hackpi/Database.py
hackpi/HackPi.py
hackpi/JWT.py
hackpi/Methods.py
hackpi/Roles.py
hackpi/Router.py
hackpi/__init__.py
hackpi-0.1.4.dist-info/METADATA
hackpi-0.1.4.dist-info/WHEEL
hackpi-0.1.4.dist-info/RECORD
